misc/moo.mp3
misc/success.mp3
WasteAndMaterialFootprint/CustomConfig.py
WasteAndMaterialFootprint/ExchangeEditor.py
WasteAndMaterialFootprint/ExplodeDatabase.py
WasteAndMaterialFootprint/FutureScenarios.py
WasteAndMaterialFootprint/MakeCustomDatabase.py
WasteAndMaterialFootprint/MethodEditor.py
WasteAndMaterialFootprint/SearchMaterial.py
WasteAndMaterialFootprint/SearchWaste.py
WasteAndMaterialFootprint/VerifyDatabase.py
WasteAndMaterialFootprint/__init__.py
WasteAndMaterialFootprint/config/__init__.py
WasteAndMaterialFootprint/config/queries_materials.py
WasteAndMaterialFootprint/config/queries_waste.py
WasteAndMaterialFootprint/config/user_settings.py
WasteAndMaterialFootprint/main.py
src/WasteAndMaterialFootprint.egg-info/PKG-INFO
src/WasteAndMaterialFootprint.egg-info/SOURCES.txt
src/WasteAndMaterialFootprint.egg-info/dependency_links.txt
src/WasteAndMaterialFootprint.egg-info/top_level.txt
src/config_backup/__init__.py
src/config_backup/queries_materials.py
src/config_backup/queries_waste.py
src/config_backup/test
src/config_backup/user_settings.py
wasteandmaterialfootprint-0.1.21.dist-info/LICENSE
wasteandmaterialfootprint-0.1.21.dist-info/METADATA
wasteandmaterialfootprint-0.1.21.dist-info/WHEEL
wasteandmaterialfootprint-0.1.21.dist-info/RECORD
