Metadata-Version: 2.1
Name: WasteAndMaterialFootprint
Version: 0.1.21
Summary: A tool for analysing waste and material footprints in Life Cycle Assessment (LCA) databases
License: CC0 1.0 Universal (CC0 1.0) Public Domain Dedication
Author: Stewart Charles McDowall
Author-email: s.c.mcdowall@cml.leidenuniv.nl
Requires-Python: >=3.10,<3.12
Classifier: Development Status :: 5 - Production/Stable
Classifier: Intended Audience :: Science/Research
Classifier: License :: CC0 1.0 Universal (CC0 1.0) Public Domain Dedication
Classifier: License :: Other/Proprietary License
Classifier: Operating System :: OS Independent
Classifier: Programming Language :: Python :: 3
Classifier: Programming Language :: Python :: 3.10
Classifier: Programming Language :: Python :: 3.11
Classifier: Topic :: Scientific/Engineering
Requires-Dist: bw2calc (>=1.8.2,<2.0.0)
Requires-Dist: bw2data (>=3.6.6,<4.0.0)
Requires-Dist: bw2io (>=0.8.12,<0.9.0)
Requires-Dist: cowsay (>=6.1,<7.0)
Requires-Dist: openpyxl (>=3.1.2,<4.0.0)
Requires-Dist: pandas (>=2.1.4,<3.0.0)
Requires-Dist: playsound (>=1.3.0,<2.0.0)
Requires-Dist: premise (>=1.8.1,<2.0.0)
Requires-Dist: premise-gwp (>=0.9.6,<0.10.0)
Requires-Dist: tqdm (>=4.66.1,<5.0.0)
Requires-Dist: wurst (>=0.4,<0.5)
